{
	"name": "ENCOM",
	"extras": {
		"vscode": [""],
		"wallpaper": [""]
	},
	"colors": {
		"background": "000000",
		"foreground": "00a595",
		"cursor": "bbbbbb",
		"selection-background": "00a48c",
		"selection-foreground": "000000",

		"black": "000000",
		"black-hg": "545454",

		"red": "9f0000",
		"red-hg": "ff0000",

		"green": "008b00",
		"green-hg": "00ee00",

		"yellow": "ffcf00",
		"yellow-hg": "ffff00",

		"blue": "0081ff",
		"blue-hg": "0000ff",

		"magenta": "bc00ca",
		"magenta-hg": "ff00ff",

		"cyan": "008b8b",
		"cyan-hg": "00cdcd",

		"white": "bbbbbb",
		"white-hg": "ffffff"
	}
}
