{
	"name": "GoaBase",
	"extras": {
		"vscode": [""],
		"wallpaper": [""]
	},
	"colors": {
		"background": "2f0033",
		"foreground": "f6ed00",
		"cursor": "1a6500",
		"selection-background": "100a24",
		"selection-foreground": "2f0033",

		"black": "880041",
		"black-hg": "411a6d",

		"red": "f78000",
		"red-hg": "f800e1",

		"green": "249000",
		"green-hg": "5743ff",

		"yellow": "f40000",
		"yellow-hg": "ea00d7",

		"blue": "000482",
		"blue-hg": "b90003",

		"magenta": "f43bff",
		"magenta-hg": "9a5952",

		"cyan": "3affff",
		"cyan-hg": "c8f9f3",

		"white": "000000",
		"white-hg": "f5f4fb"
	}
}
