{
	"name": "Snazzy",
	"extras": {
		"vscode": ["Night Owl"],
		"wallpaper": ["~/.config/gtheme/wallpapers/Snazzy/sunset-mountain.jpg"]
	},
	"colors": {
		"background": "112031",
		"foreground": "F1F1F0",
		"cursor": "97979B",
		"selection-background": "FFFACD",
		"selection-foreground": "000000",

		"black": "112031",
		"black-hg": "686868",

		"red": "FF5C57",
		"red-hg": "FF5C57",

		"green": "5AF78E",
		"green-hg": "5AF78E",

		"yellow": "F3F99D",
		"yellow-hg": "F3F99D",

		"blue": "57C7FF",
		"blue-hg": "57C7FF",

		"magenta": "FF6AC1",
		"magenta-hg": "FF6AC1",

		"cyan": "9AEDFE",
		"cyan-hg": "9AEDFE",

		"white": "F1F1F0",
		"white-hg": "F1F1F0"
	}
}
